pulse_django_mcp/__init__.py
pulse_django_mcp/apps.py
pulse_django_mcp/config.py
pulse_django_mcp/discovery.py
pulse_django_mcp/discovery_utils.py
pulse_django_mcp/http_tools.py
pulse_django_mcp/integration.py
pulse_django_mcp/management/__init__.py
pulse_django_mcp/management/commands/__init__.py
pulse_django_mcp/management/commands/mcp_list_tools.py
pulse_django_mcp/mcp_server.py
pulse_django_mcp/urls.py
pulse_django_mcp/utils.py
pulse_django_mcp-0.2.2.dist-info/LICENSE.txt
pulse_django_mcp-0.2.2.dist-info/METADATA
pulse_django_mcp-0.2.2.dist-info/WHEEL
pulse_django_mcp-0.2.2.dist-info/RECORD
