Metadata-Version: 2.1
Name: pulse_django_mcp
Version: 0.2.2
Summary: Django integration for Model Context Protocol (MCP).
License: MIT
Author: Fernando Cañizares Romero
Author-email: fcrfercanrom@gmail.com
Requires-Python: >=3.10
Classifier: License :: OSI Approved :: MIT License
Classifier: Programming Language :: Python :: 3
Classifier: Programming Language :: Python :: 3.10
Classifier: Programming Language :: Python :: 3.11
Classifier: Programming Language :: Python :: 3.12
Classifier: Programming Language :: Python :: 3.13
Requires-Dist: django (>=3.2)
Requires-Dist: djangorestframework (>=3.16.0,<4.0.0)
Requires-Dist: mcp (>=1.6.0)
Requires-Dist: pydantic (>=2.0)
